Workbook

Sheet 月度经营表
A1: 餐厅月度经营表
A2: 录入黄色单元格；绿色单元格为自动计算结果。金额单位：元
A4: 月份 | B4: 营业收入（元） | C4: 食材成本（元） | D4: 人工（元） | E4: 租金（元） | F4: 水电（元） | G4: 毛利（元） | H4: 毛利率
A5: 1月 | G5: =B5-C5-D5-E5-F5 -> 0 | H5: =IF(OR(B5="",B5=0),"",G5/B5)
A6: 2月 | G6: =B6-C6-D6-E6-F6 -> 0 | H6: =IF(OR(B6="",B6=0),"",G6/B6)
A7: 3月 | G7: =B7-C7-D7-E7-F7 -> 0 | H7: =IF(OR(B7="",B7=0),"",G7/B7)
A8: 4月 | G8: =B8-C8-D8-E8-F8 -> 0 | H8: =IF(OR(B8="",B8=0),"",G8/B8)
A9: 5月 | G9: =B9-C9-D9-E9-F9 -> 0 | H9: =IF(OR(B9="",B9=0),"",G9/B9)
A10: 6月 | G10: =B10-C10-D10-E10-F10 -> 0 | H10: =IF(OR(B10="",B10=0),"",G10/B10)
A11: 7月 | G11: =B11-C11-D11-E11-F11 -> 0 | H11: =IF(OR(B11="",B11=0),"",G11/B11)
A12: 8月 | G12: =B12-C12-D12-E12-F12 -> 0 | H12: =IF(OR(B12="",B12=0),"",G12/B12)
A13: 9月 | G13: =B13-C13-D13-E13-F13 -> 0 | H13: =IF(OR(B13="",B13=0),"",G13/B13)
A14: 10月 | G14: =B14-C14-D14-E14-F14 -> 0 | H14: =IF(OR(B14="",B14=0),"",G14/B14)
A15: 11月 | G15: =B15-C15-D15-E15-F15 -> 0 | H15: =IF(OR(B15="",B15=0),"",G15/B15)
A16: 12月 | G16: =B16-C16-D16-E16-F16 -> 0 | H16: =IF(OR(B16="",B16=0),"",G16/B16)
A17: 全年合计 | B17: =SUM(B5:B16) -> 0 | C17: =SUM(C5:C16) -> 0 | D17: =SUM(D5:D16) -> 0 | E17: =SUM(E5:E16) -> 0 | F17: =SUM(F5:F16) -> 0 | G17: =SUM(G5:G16) -> 0 | H17: =IF(OR(B17="",B17=0),"",G17/B17)

Sheet 季度汇总
A1: 餐厅季度经营汇总
A2: 季度毛利率按季度毛利 ÷ 季度营业收入计算，不对月度毛利率做简单平均。
A4: 月份 | B4: 营业收入（元） | C4: 食材成本（元） | D4: 人工（元） | E4: 租金（元） | F4: 水电（元） | G4: 毛利（元） | H4: 毛利率
A5: 一季度 | B5: =SUM('月度经营表'!B5:B7) -> 0 | C5: =SUM('月度经营表'!C5:C7) -> 0 | D5: =SUM('月度经营表'!D5:D7) -> 0 | E5: =SUM('月度经营表'!E5:E7) -> 0 | F5: =SUM('月度经营表'!F5:F7) -> 0 | G5: =B5-C5-D5-E5-F5 -> 0 | H5: =IF(OR(B5="",B5=0),"",G5/B5)
A6: 二季度 | B6: =SUM('月度经营表'!B8:B10) -> 0 | C6: =SUM('月度经营表'!C8:C10) -> 0 | D6: =SUM('月度经营表'!D8:D10) -> 0 | E6: =SUM('月度经营表'!E8:E10) -> 0 | F6: =SUM('月度经营表'!F8:F10) -> 0 | G6: =B6-C6-D6-E6-F6 -> 0 | H6: =IF(OR(B6="",B6=0),"",G6/B6)
A7: 三季度 | B7: =SUM('月度经营表'!B11:B13) -> 0 | C7: =SUM('月度经营表'!C11:C13) -> 0 | D7: =SUM('月度经营表'!D11:D13) -> 0 | E7: =SUM('月度经营表'!E11:E13) -> 0 | F7: =SUM('月度经营表'!F11:F13) -> 0 | G7: =B7-C7-D7-E7-F7 -> 0 | H7: =IF(OR(B7="",B7=0),"",G7/B7)
A8: 四季度 | B8: =SUM('月度经营表'!B14:B16) -> 0 | C8: =SUM('月度经营表'!C14:C16) -> 0 | D8: =SUM('月度经营表'!D14:D16) -> 0 | E8: =SUM('月度经营表'!E14:E16) -> 0 | F8: =SUM('月度经营表'!F14:F16) -> 0 | G8: =B8-C8-D8-E8-F8 -> 0 | H8: =IF(OR(B8="",B8=0),"",G8/B8)
A9: 全年合计 | B9: =SUM(B5:B8) -> 0 | C9: =SUM(C5:C8) -> 0 | D9: =SUM(D5:D8) -> 0 | E9: =SUM(E5:E8) -> 0 | F9: =SUM(F5:F8) -> 0 | G9: =SUM(G5:G8) -> 0 | H9: =IF(OR(B9="",B9=0),"",G9/B9)
