Workbook

Sheet 月度明细
A1: 小型工作室 2025 年度预算
A2: 单位：人民币（元）｜蓝色金额为可直接修改的示例预算，合计与净利润自动计算
A3: 月份 | B3: 项目/服务收入 | C3: 其他收入 | D3: 收入合计 | E3: 人员薪酬 | F3: 房租与水电 | G3: 软件与订阅 | H3: 市场推广 | I3: 设备与耗材 | J3: 差旅与业务招待 | K3: 税费与行政 | L3: 其他支出 | M3: 支出合计 | N3: 净利润
A4: 2025年1月 | B4: 32000 | C4: 1800 | D4: =SUM(B4:C4) -> 33800 | E4: 9000 | F4: 2200 | G4: 3500 | H4: 1500 | I4: 1800 | J4: 2600 | K4: 2800 | L4: 500 | M4: =SUM(E4:L4) -> 41900 | N4: =D4-M4 -> -8100
A5: 2025年2月 | B5: 36000 | C5: 2000 | D5: =SUM(B5:C5) -> 38000 | E5: 9000 | F5: 2200 | G5: 3500 | H5: 1800 | I5: 1600 | J5: 2500 | K5: 3000 | L5: 600 | M5: =SUM(E5:L5) -> 43200 | N5: =D5-M5 -> -5200
A6: 2025年3月 | B6: 42000 | C6: 2200 | D6: =SUM(B6:C6) -> 44200 | E6: 9000 | F6: 2200 | G6: 4200 | H6: 2200 | I6: 2400 | J6: 2700 | K6: 3300 | L6: 600 | M6: =SUM(E6:L6) -> 47100 | N6: =D6-M6 -> -2900
A7: 2025年4月 | B7: 39000 | C7: 1800 | D7: =SUM(B7:C7) -> 40800 | E7: 9200 | F7: 2300 | G7: 3800 | H7: 1800 | I7: 2200 | J7: 2800 | K7: 3200 | L7: 600 | M7: =SUM(E7:L7) -> 46900 | N7: =D7-M7 -> -6100
A8: 2025年5月 | B8: 45000 | C8: 2500 | D8: =SUM(B8:C8) -> 47500 | E8: 9200 | F8: 2300 | G8: 4000 | H8: 2200 | I8: 2600 | J8: 3000 | K8: 3500 | L8: 700 | M8: =SUM(E8:L8) -> 49500 | N8: =D8-M8 -> -2000
A9: 2025年6月 | B9: 48000 | C9: 2600 | D9: =SUM(B9:C9) -> 50600 | E9: 9200 | F9: 2300 | G9: 4200 | H9: 2500 | I9: 2800 | J9: 3000 | K9: 3600 | L9: 700 | M9: =SUM(E9:L9) -> 50800 | N9: =D9-M9 -> -200
A10: 2025年7月 | B10: 43000 | C10: 2200 | D10: =SUM(B10:C10) -> 45200 | E10: 9500 | F10: 2300 | G10: 4000 | H10: 1800 | I10: 2200 | J10: 3000 | K10: 3400 | L10: 700 | M10: =SUM(E10:L10) -> 49900 | N10: =D10-M10 -> -4700
A11: 2025年8月 | B11: 46000 | C11: 2400 | D11: =SUM(B11:C11) -> 48400 | E11: 9500 | F11: 2300 | G11: 4000 | H11: 2000 | I11: 2400 | J11: 3100 | K11: 3500 | L11: 700 | M11: =SUM(E11:L11) -> 51000 | N11: =D11-M11 -> -2600
A12: 2025年9月 | B12: 52000 | C12: 2800 | D12: =SUM(B12:C12) -> 54800 | E12: 9500 | F12: 2300 | G12: 4500 | H12: 2600 | I12: 3000 | J12: 3200 | K12: 3800 | L12: 800 | M12: =SUM(E12:L12) -> 54200 | N12: =D12-M12 -> 600
A13: 2025年10月 | B13: 50000 | C13: 2600 | D13: =SUM(B13:C13) -> 52600 | E13: 9800 | F13: 2400 | G13: 4300 | H13: 2300 | I13: 2800 | J13: 3200 | K13: 3700 | L13: 800 | M13: =SUM(E13:L13) -> 54300 | N13: =D13-M13 -> -1700
A14: 2025年11月 | B14: 56000 | C14: 3000 | D14: =SUM(B14:C14) -> 59000 | E14: 9800 | F14: 2400 | G14: 4600 | H14: 2800 | I14: 3200 | J14: 3400 | K14: 4000 | L14: 800 | M14: =SUM(E14:L14) -> 56500 | N14: =D14-M14 -> 2500
A15: 2025年12月 | B15: 62000 | C15: 3500 | D15: =SUM(B15:C15) -> 65500 | E15: 10000 | F15: 2500 | G15: 4800 | H15: 3200 | I15: 3600 | J15: 3500 | K15: 4500 | L15: 900 | M15: =SUM(E15:L15) -> 59500 | N15: =D15-M15 -> 6000
A16: 年度合计 | B16: =SUM(B4:B15) -> 551000 | C16: =SUM(C4:C15) -> 29400 | D16: =SUM(D4:D15) -> 580400 | E16: =SUM(E4:E15) -> 112700 | F16: =SUM(F4:F15) -> 27700 | G16: =SUM(G4:G15) -> 49400 | H16: =SUM(H4:H15) -> 26700 | I16: =SUM(I4:I15) -> 30600 | ... N16: =SUM(N4:N15) -> -24400

Sheet 季度汇总
A1: 小型工作室 2025 年季度预算汇总
A2: 数据通过公式引用“月度明细”表，可回到明细表修改示例预算。
A3: 季度 | B3: 收入合计 | C3: 人员薪酬 | D3: 房租与水电 | E3: 软件与订阅 | F3: 市场推广 | G3: 设备与耗材 | H3: 差旅与业务招待 | I3: 税费与行政 | J3: 其他支出 | K3: 支出合计 | L3: 净利润
A4: Q1 | B4: =SUM('月度明细'!D4:D7) -> 156800 | C4: =SUM('月度明细'!E4:E7) -> 36200 | D4: =SUM('月度明细'!F4:F7) -> 8900 | E4: =SUM('月度明细'!G4:G7) -> 15000 | F4: =SUM('月度明细'!H4:H7) -> 7300 | G4: =SUM('月度明细'!I4:I7) -> 8000 | H4: =SUM('月度明细'!J4:J7) -> 10600 | I4: =SUM('月度明细'!K4:K7) -> 12300 | ... L4: =SUM('月度明细'!N4:N7) -> -22300
A5: Q2 | B5: =SUM('月度明细'!D8:D11) -> 191700 | C5: =SUM('月度明细'!E8:E11) -> 37400 | D5: =SUM('月度明细'!F8:F11) -> 9200 | E5: =SUM('月度明细'!G8:G11) -> 16200 | F5: =SUM('月度明细'!H8:H11) -> 8500 | G5: =SUM('月度明细'!I8:I11) -> 10000 | H5: =SUM('月度明细'!J8:J11) -> 12100 | I5: =SUM('月度明细'!K8:K11) -> 14000 | ... L5: =SUM('月度明细'!N8:N11) -> -9500
A6: Q3 | B6: =SUM('月度明细'!D12:D15) -> 231900 | C6: =SUM('月度明细'!E12:E15) -> 39100 | D6: =SUM('月度明细'!F12:F15) -> 9600 | E6: =SUM('月度明细'!G12:G15) -> 18200 | F6: =SUM('月度明细'!H12:H15) -> 10900 | G6: =SUM('月度明细'!I12:I15) -> 12600 | H6: =SUM('月度明细'!J12:J15) -> 13300 | I6: =SUM('月度明细'!K12:K15) -> 16000 | ... L6: =SUM('月度明细'!N12:N15) -> 7400
A7: Q4 | B7: =SUM('月度明细'!D16:D19) -> 0 | C7: =SUM('月度明细'!E16:E19) -> 0 | D7: =SUM('月度明细'!F16:F19) -> 0 | E7: =SUM('月度明细'!G16:G19) -> 0 | F7: =SUM('月度明细'!H16:H19) -> 0 | G7: =SUM('月度明细'!I16:I19) -> 0 | H7: =SUM('月度明细'!J16:J19) -> 0 | I7: =SUM('月度明细'!K16:K19) -> 0 | ... L7: =SUM('月度明细'!N16:N19) -> 0
A8: 年度合计 | B8: =SUM(B4:B7) -> 580400 | C8: =SUM(C4:C7) -> 112700 | D8: =SUM(D4:D7) -> 27700 | E8: =SUM(E4:E7) -> 49400 | F8: =SUM(F4:F7) -> 26700 | G8: =SUM(G4:G7) -> 30600 | H8: =SUM(H4:H7) -> 36000 | I8: =SUM(I4:I7) -> 42300 | ... L8: =SUM(L4:L7) -> -24400

Sheet 假设说明
A1: 小型工作室 2025 年度预算假设说明
A2: 以下假设用于解释预填示例预算，实际使用时可按经营情况调整。
A3: 序号 | B3: 假设主题 | C3: 说明
A4: 1 | B4: 预算年度 | C4: 预算覆盖 2025 年 1 月至 12 月，按月记录并按季度汇总。
A5: 2 | B5: 项目与其他收入 | C5: 收入分为项目/服务收入与其他收入，示例金额用于展示常见的季节性变化。
A6: 3 | B6: 人员薪酬、房租与水电 | C6: 人员薪酬及场地相关费用按月预留，默认工作室全年持续运营。
A7: 4 | B7: 软件、推广、设备、差旅及行政 | C7: 软件订阅、市场推广、设备耗材、差旅招待、税费行政和其他支出均按月预算。
A8: 5 | B8: 人民币示例预算 | C8: 所有金额以人民币元展示；蓝色金额为可直接修改的示例输入，合计与净利润由公式计算。
